lineleak.py
flake8_lineleak-1.0.2.dist-info/LICENSE
flake8_lineleak-1.0.2.dist-info/METADATA
flake8_lineleak-1.0.2.dist-info/WHEEL
flake8_lineleak-1.0.2.dist-info/entry_points.txt
flake8_lineleak-1.0.2.dist-info/top_level.txt
flake8_lineleak-1.0.2.dist-info/RECORD
