Metadata-Version: 2.1
Name: flake8-lineleak
Version: 1.0.2
Summary: Lineleak is a flake8 plugin that counts the lines containing live code in a script, and 'yells' if a set limit is exceeded. It is meant to help enforce short scripts and modular python programming.
Home-page: https://github.com/ayivima/flake8-lineleak
Author: Victor Mawusi Ayi
Author-email: ayivima@hotmail.com
License: MIT
Keywords: flake8,lineleak,counter,lines,plugin
Platform: UNKNOWN
Classifier: Development Status :: 3 - Alpha
Classifier: Environment :: Console
Classifier: Framework :: Flake8
Classifier: Intended Audience :: Developers
Classifier: License :: OSI Approved :: MIT License
Classifier: Operating System :: OS Independent
Classifier: Programming Language :: Python
Classifier: Programming Language :: Python :: 3.5
Classifier: Programming Language :: Python :: 3.6
Classifier: Programming Language :: Python :: 3.7
Classifier: Programming Language :: Python :: 3 :: Only
Classifier: Topic :: Software Development :: Libraries :: Python Modules
Classifier: Topic :: Software Development :: Quality Assurance
Requires-Python: >=3.4
Requires-Dist: flake8 (>=3.3.0)
Requires-Dist: attrs
